Metadata-Version: 2.1
Name: python-openhab-logsaver
Version: 1.0.0
Summary: Save openHAB logs into a database.
Home-page: https://github.com/Michdo93/python-openhab-logsaver
Download-URL: https://github.com/Michdo93/python-openhab-logsaver
Author: Michael Dörflinger
Author-email: michaeldoerflinger93@gmail.com
License: MIT License
Project-URL: Bug Tracker, https://github.com/Michdo93/python-openhab-logsaver/issues
Project-URL: Documentation, https://github.com/Michdo93/python-openhab-logsaver/blob/main/README.md
Project-URL: Source Code, https://github.com/Michdo93/python-openhab-logsaver
Keywords: openHAB
Classifier: Development Status :: 4 - Beta
Classifier: License :: OSI Approved :: MIT License
Classifier: Intended Audience :: Developers
Classifier: Operating System :: OS Independent
Classifier: Programming Language :: Python :: 3
Classifier: Programming Language :: Python :: 3 :: Only
Requires-Python: >=3.5
License-File: LICENSE
Requires-Dist: mariadb (>=1.0.10)
